setup.cfg
setup.py
webmocker/__init__.py
webmocker/sample_test.py
webmocker/server.py
webmocker/stubbing_engine.py
webmocker.egg-info/PKG-INFO
webmocker.egg-info/SOURCES.txt
webmocker.egg-info/dependency_links.txt
webmocker.egg-info/requires.txt
webmocker.egg-info/top_level.txt
webmocker/mock_helper/HttpMock.py
webmocker/mock_helper/MockRequest.py
webmocker/mock_helper/MockResponse.py
webmocker/mock_helper/__init__.py
webmocker/mock_helper/pretend_helpers.py
webmocker/mock_helper/pretender_defaults.py