Metadata-Version: 1.1
Name: webmocker
Version: 0.5
Summary: A test lib for stubbing http response
Home-page: https://github.com/sheltonpaul89/web-mocker
Author: Shelton Paul
Author-email: sheltonpaul89@gmail.com
License: UNKNOWN
Download-URL: https://github.com/sheltonpaul89/web-mocker/tarball/0.1
Keywords: web,stubbing,http,mock,Web Stubs
Platform: UNKNOWN
